{
  "generated_at": "2026-03-31T05:39:44.625366Z",
  "rows": [
    {
      "time": "00:10",
      "match": "Интернасьональ Богота - Хуниор",
      "country": "co",
      "p1": "57%",
      "px": "19%",
      "p2": "23%",
      "bet": "П1",
      "odd1": "2.08",
      "oddx": "3.30",
      "odd2": "3.40",
      "result": "0:1"
    },
    {
      "time": "00:30",
      "match": "Ботафого ПБ - Арапирака",
      "country": "br",
      "p1": "66%",
      "px": "21%",
      "p2": "13%",
      "bet": "П1",
      "odd1": "1.70",
      "oddx": "3.10",
      "odd2": "5.90",
      "result": "2:2"
    },
    {
      "time": "01:00",
      "match": "Доминиканская Респ. - Куба",
      "country": "world",
      "p1": "43%",
      "px": "15%",
      "p2": "43%",
      "bet": "12",
      "odd1": "1.32",
      "oddx": "4.90",
      "odd2": "9.80",
      "result": "1:1"
    },
    {
      "time": "01:30",
      "match": "Пеньяроль - Расинг Монтевидео",
      "country": "uy",
      "p1": "55%",
      "px": "18%",
      "p2": "27%",
      "bet": "П1",
      "odd1": "1.68",
      "oddx": "3.30",
      "odd2": "5.50",
      "result": "1:2"
    },
    {
      "time": "01:30",
      "match": "Атлетико Паранаэнсе - Ботафого РЖ",
      "country": "br",
      "p1": "49%",
      "px": "19%",
      "p2": "33%",
      "bet": "12",
      "odd1": "2.02",
      "oddx": "3.20",
      "odd2": "3.90",
      "result": "4:1"
    },
    {
      "time": "09:00",
      "match": "Новая Зеландия - Чили",
      "country": "world",
      "p1": "15%",
      "px": "19%",
      "p2": "66%",
      "bet": "П2",
      "odd1": "6.70",
      "oddx": "4.00",
      "odd2": "1.50",
      "result": "4:1"
    },
    {
      "time": "11:30",
      "match": "Ст. Киттс и Невис - Соломоновы Острова",
      "country": "world",
      "p1": "67%",
      "px": "16%",
      "p2": "17%",
      "bet": "П1",
      "odd1": "1.55",
      "oddx": "5.10",
      "odd2": "4.50",
      "result": "4:2"
    },
    {
      "time": "12:30",
      "match": "Мельбурн Виктори ВПЛ - Лангваррин",
      "country": "au",
      "p1": "66%",
      "px": "15%",
      "p2": "19%",
      "bet": "П1",
      "odd1": "1.65",
      "oddx": "4.60",
      "odd2": "3.60",
      "result": "3:3"
    },
    {
      "time": "13:00",
      "match": "Тринидад и Тобаго - Габон",
      "country": "world",
      "p1": "14%",
      "px": "17%",
      "p2": "69%",
      "bet": "П2",
      "odd1": "5.50",
      "oddx": "4.30",
      "odd2": "1.58",
      "result": "2:2"
    },
    {
      "time": "15:00",
      "match": "Россия (мол) - Иордания (мол)",
      "country": "world",
      "p1": "47%",
      "px": "30%",
      "p2": "22%",
      "bet": "1X",
      "odd1": "0.00",
      "oddx": "0.00",
      "odd2": "0.00",
      "result": "отм"
    },
    {
      "time": "16:00",
      "match": "Индонезия - Болгария",
      "country": "world",
      "p1": "25%",
      "px": "35%",
      "p2": "40%",
      "bet": "X2",
      "odd1": "2.35",
      "oddx": "3.50",
      "odd2": "2.85",
      "result": "0:1"
    },
    {
      "time": "17:00",
      "match": "Узбекистан - Венесуэла",
      "country": "world",
      "p1": "61%",
      "px": "19%",
      "p2": "20%",
      "bet": "П1",
      "odd1": "2.40",
      "oddx": "3.40",
      "odd2": "3.00",
      "result": "0:0"
    },
    {
      "time": "17:00",
      "match": "Гренада - Кения",
      "country": "world",
      "p1": "39%",
      "px": "12%",
      "p2": "49%",
      "bet": "12",
      "odd1": "15.00",
      "oddx": "8.70",
      "odd2": "1.16",
      "result": "0:3"
    },
    {
      "time": "17:00",
      "match": "Одд - Люн",
      "country": "world",
      "p1": "55%",
      "px": "17%",
      "p2": "29%",
      "bet": "П1",
      "odd1": "2.20",
      "oddx": "3.70",
      "odd2": "2.65",
      "result": "2:1"
    },
    {
      "time": "17:30",
      "match": "Дахук - Захо",
      "country": "iq",
      "p1": "41%",
      "px": "37%",
      "p2": "23%",
      "bet": "1X",
      "odd1": "3.10",
      "oddx": "2.30",
      "odd2": "3.10",
      "result": "0:1"
    },
    {
      "time": "18:00",
      "match": "Азербайджан - Сьерра-Леоне",
      "country": "world",
      "p1": "53%",
      "px": "18%",
      "p2": "29%",
      "bet": "12",
      "odd1": "1.75",
      "oddx": "3.70",
      "odd2": "4.90",
      "result": "1:1"
    },
    {
      "time": "19:00",
      "match": "Кипр - Молдова",
      "country": "world",
      "p1": "71%",
      "px": "17%",
      "p2": "13%",
      "bet": "П1",
      "odd1": "1.68",
      "oddx": "3.60",
      "odd2": "5.20",
      "result": "3:2"
    },
    {
      "time": "19:30",
      "match": "Нидерланды (мол) - Бельгия (мол)",
      "country": "world",
      "p1": "61%",
      "px": "17%",
      "p2": "23%",
      "bet": "П1",
      "odd1": "2.28",
      "oddx": "3.90",
      "odd2": "2.65",
      "result": "2:1"
    },
    {
      "time": "20:00",
      "match": "Франция (мол) - Исландия (мол)",
      "country": "world",
      "p1": "69%",
      "px": "9%",
      "p2": "21%",
      "bet": "П1",
      "odd1": "1.16",
      "oddx": "7.00",
      "odd2": "13.00",
      "result": "2:1"
    },
    {
      "time": "20:30",
      "match": "Руанда - Эстония",
      "country": "world",
      "p1": "61%",
      "px": "20%",
      "p2": "20%",
      "bet": "П1",
      "odd1": "1.50",
      "oddx": "4.10",
      "odd2": "7.30",
      "result": "2:0"
    },
    {
      "time": "21:00",
      "match": "Расинг Клуб (рез) - Альдосиви (рез)",
      "country": "ar",
      "p1": "51%",
      "px": "17%",
      "p2": "32%",
      "bet": "12",
      "odd1": "1.65",
      "oddx": "3.50",
      "odd2": "4.80",
      "result": "1:0"
    },
    {
      "time": "21:30",
      "match": "Ареццо - Асколи",
      "country": "it",
      "p1": "27%",
      "px": "37%",
      "p2": "35%",
      "bet": "X2",
      "odd1": "2.20",
      "oddx": "2.90",
      "odd2": "3.50",
      "result": "1:2"
    },
    {
      "time": "21:30",
      "match": "Казертана - Сорренто",
      "country": "it",
      "p1": "69%",
      "px": "18%",
      "p2": "13%",
      "bet": "П1",
      "odd1": "1.52",
      "oddx": "4.00",
      "odd2": "5.80",
      "result": "2:0"
    },
    {
      "time": "21:30",
      "match": "Кумбран Селтик - Трефелин",
      "country": "wales",
      "p1": "37%",
      "px": "8%",
      "p2": "55%",
      "bet": "П2",
      "odd1": "15.00",
      "oddx": "10.50",
      "odd2": "1.07",
      "result": "1:8"
    },
    {
      "time": "21:45",
      "match": "Германия - Гана",
      "country": "world",
      "p1": "85%",
      "px": "9%",
      "p2": "5%",
      "bet": "П1",
      "odd1": "1.14",
      "oddx": "8.90",
      "odd2": "16.00",
      "result": "2:1"
    },
    {
      "time": "22:00",
      "match": "Альфтанес - Кари",
      "country": "is",
      "p1": "39%",
      "px": "9%",
      "p2": "51%",
      "bet": "12",
      "odd1": "11.50",
      "oddx": "6.40",
      "odd2": "1.17",
      "result": "5:1"
    },
    {
      "time": "22:00",
      "match": "Гайана - Белиз",
      "country": "world",
      "p1": "55%",
      "px": "15%",
      "p2": "29%",
      "bet": "П1",
      "odd1": "1.45",
      "oddx": "4.80",
      "odd2": "6.00",
      "result": "3:1"
    },
    {
      "time": "22:00",
      "match": "Дефенсорес Бельграно - Рафаэла",
      "country": "ar",
      "p1": "28%",
      "px": "40%",
      "p2": "32%",
      "bet": "X2",
      "odd1": "2.24",
      "oddx": "2.45",
      "odd2": "4.40",
      "result": "1:1"
    }
  ]
}